ig_x509/__init__.py
ig_x509/certificate.py
ig_x509/combine.py
ig_x509/copy_model.py
ig_x509/decrypt.py
ig_x509/encrypt.py
ig_x509/split_decrypted.py
ig_x509/split_json.py
ishan_x509-0.1.0.dist-info/LICENSE
ishan_x509-0.1.0.dist-info/METADATA
ishan_x509-0.1.0.dist-info/WHEEL
ishan_x509-0.1.0.dist-info/top_level.txt
ishan_x509-0.1.0.dist-info/RECORD
