Metadata-Version: 2.1
Name: ishan_x509
Version: 0.1.0
Summary: x509 certificates
Author: Ishan Gupta
Author-email: ishangupta2312@gmail.com
Classifier: Programming Language :: Python :: 3
Classifier: License :: OSI Approved :: MIT License
Classifier: Operating System :: OS Independent
Requires-Python: >=3.6
License-File: LICENSE
Requires-Dist: cryptography
